ai.py
aidotpy-0.3.1.dist-info/LICENSE
aidotpy-0.3.1.dist-info/METADATA
aidotpy-0.3.1.dist-info/WHEEL
aidotpy-0.3.1.dist-info/entry_points.txt
aidotpy-0.3.1.dist-info/top_level.txt
aidotpy-0.3.1.dist-info/RECORD
