Metadata-Version: 2.1
Name: aidotpy
Version: 0.3.1
Home-page: 
Author: 
Author-email: 
License-File: LICENSE
